oeis/__init__.py
oeis/_version.py
oeis/base.py
oeis/client.py
oeis/sequence.py
oeis/util.py
oeis/generators/__init__.py
oeis_api-0.1.0.dist-info/LICENSE
oeis_api-0.1.0.dist-info/METADATA
oeis_api-0.1.0.dist-info/WHEEL
oeis_api-0.1.0.dist-info/top_level.txt
oeis_api-0.1.0.dist-info/RECORD
