Metadata-Version: 2.1
Name: oeis-api
Version: 0.1.0
Summary: interface to the OEIS
Home-page: https://github.com/bhgomes/oeis
Author: Brandon Gomes
Author-email: bhgomes.github@gmail.com
License: MIT
Platform: UNKNOWN
Classifier: License :: OSI Approved :: MIT License
Classifier: Programming Language :: Python
Classifier: Programming Language :: Python :: 3
Classifier: Programming Language :: Python :: 3 :: Only
Classifier: Programming Language :: Python :: 3.5
Classifier: Programming Language :: Python :: 3.6
Classifier: Programming Language :: Python :: 3.7
Classifier: Development Status :: 1 - Planning
Requires-Python: >=3.6.0
Requires-Dist: numpy
Requires-Dist: sympy
Requires-Dist: wrapt
Requires-Dist: python-box
